llm_event_digest/__init__.py
llm_event_digest/main.py
llm_event_digest/prompts.py
llm_event_digest-2025.12.21181028.dist-info/METADATA
llm_event_digest-2025.12.21181028.dist-info/WHEEL
llm_event_digest-2025.12.21181028.dist-info/top_level.txt
llm_event_digest-2025.12.21181028.dist-info/RECORD
