Metadata-Version: 2.4
Name: llm-event-digest
Version: 2025.12.21181028
Summary: A new package that processes news headlines or short text inputs to generate structured summaries of events, such as service disruptions or incidents. It uses an LLM to extract key details like the co
Author-email: llm-event-digest <hi@eugene.plus>
License: MIT
Project-URL: Homepage, https://github.com/chigwell/llm-event-digest
Requires-Python: >=3.9
Requires-Dist: langchain-llm7>=0.0.0
Requires-Dist: llmatch-messages>=0.0.0
Requires-Dist: langchain-core>=0.3.0
